<?xml version='1.0' encoding='utf8'?>
<Gesture Name="circle4" Subject="2" Speed="Medium" Number="4" NumPts="129" Milliseconds="169168" AppName="Gestures" AppVersion="1.0.0.0" Date="Thursday, March 02, 2023" TimeOfDay="01:56:30 AM"><Point X="184" Y="231" />
 	<Point X="181" Y="231" />
 	<Point X="175" Y="232" />
 	<Point X="170" Y="234" />
 	<Point X="166" Y="235" />
 	<Point X="161" Y="238" />
 	<Point X="158" Y="239" />
 	<Point X="154" Y="240" />
 	<Point X="153" Y="242" />
 	<Point X="151" Y="243" />
 	<Point X="149" Y="244" />
 	<Point X="147" Y="245" />
 	<Point X="146" Y="246" />
 	<Point X="145" Y="247" />
 	<Point X="142" Y="249" />
 	<Point X="140" Y="253" />
 	<Point X="138" Y="255" />
 	<Point X="134" Y="259" />
 	<Point X="133" Y="262" />
 	<Point X="130" Y="267" />
 	<Point X="127" Y="271" />
 	<Point X="125" Y="277" />
 	<Point X="122" Y="285" />
 	<Point X="122" Y="291" />
 	<Point X="122" Y="294" />
 	<Point X="122" Y="296" />
 	<Point X="122" Y="299" />
 	<Point X="122" Y="300" />
 	<Point X="122" Y="302" />
 	<Point X="122" Y="303" />
 	<Point X="122" Y="304" />
 	<Point X="122" Y="305" />
 	<Point X="122" Y="307" />
 	<Point X="122" Y="309" />
 	<Point X="122" Y="311" />
 	<Point X="124" Y="312" />
 	<Point X="128" Y="315" />
 	<Point X="131" Y="316" />
 	<Point X="136" Y="318" />
 	<Point X="139" Y="319" />
 	<Point X="144" Y="320" />
 	<Point X="147" Y="321" />
 	<Point X="152" Y="323" />
 	<Point X="158" Y="323" />
 	<Point X="161" Y="323" />
 	<Point X="166" Y="323" />
 	<Point X="171" Y="323" />
 	<Point X="174" Y="323" />
 	<Point X="180" Y="324" />
 	<Point X="183" Y="324" />
 	<Point X="187" Y="324" />
 	<Point X="189" Y="324" />
 	<Point X="192" Y="324" />
 	<Point X="194" Y="324" />
 	<Point X="198" Y="324" />
 	<Point X="202" Y="324" />
 	<Point X="206" Y="323" />
 	<Point X="212" Y="321" />
 	<Point X="214" Y="320" />
 	<Point X="217" Y="319" />
 	<Point X="220" Y="318" />
 	<Point X="222" Y="318" />
 	<Point X="223" Y="317" />
 	<Point X="226" Y="316" />
 	<Point X="226" Y="315" />
 	<Point X="228" Y="315" />
 	<Point X="229" Y="314" />
 	<Point X="230" Y="314" />
 	<Point X="232" Y="312" />
 	<Point X="233" Y="311" />
 	<Point X="234" Y="309" />
 	<Point X="236" Y="307" />
 	<Point X="237" Y="303" />
 	<Point X="238" Y="299" />
 	<Point X="238" Y="295" />
 	<Point X="239" Y="290" />
 	<Point X="239" Y="284" />
 	<Point X="239" Y="281" />
 	<Point X="239" Y="277" />
 	<Point X="239" Y="275" />
 	<Point X="238" Y="272" />
 	<Point X="238" Y="270" />
 	<Point X="238" Y="268" />
 	<Point X="236" Y="266" />
 	<Point X="235" Y="264" />
 	<Point X="234" Y="263" />
 	<Point X="234" Y="260" />
 	<Point X="234" Y="258" />
 	<Point X="232" Y="254" />
 	<Point X="231" Y="252" />
 	<Point X="229" Y="249" />
 	<Point X="227" Y="246" />
 	<Point X="226" Y="244" />
 	<Point X="225" Y="242" />
 	<Point X="222" Y="240" />
 	<Point X="221" Y="239" />
 	<Point X="219" Y="238" />
 	<Point X="217" Y="236" />
 	<Point X="216" Y="236" />
 	<Point X="215" Y="235" />
 	<Point X="214" Y="235" />
 	<Point X="213" Y="235" />
 	<Point X="211" Y="234" />
 	<Point X="210" Y="233" />
 	<Point X="209" Y="233" />
 	<Point X="208" Y="233" />
 	<Point X="206" Y="233" />
 	<Point X="205" Y="233" />
 	<Point X="204" Y="232" />
 	<Point X="203" Y="232" />
 	<Point X="202" Y="232" />
 	<Point X="200" Y="231" />
 	<Point X="199" Y="231" />
 	<Point X="198" Y="231" />
 	<Point X="197" Y="231" />
 	<Point X="195" Y="231" />
 	<Point X="194" Y="231" />
 	<Point X="193" Y="230" />
 	<Point X="192" Y="230" />
 	<Point X="190" Y="230" />
 	<Point X="189" Y="230" />
 	<Point X="188" Y="230" />
 	<Point X="187" Y="230" />
 	<Point X="186" Y="230" />
 	<Point X="185" Y="230" />
 	<Point X="184" Y="230" />
 	<Point X="183" Y="230" />
 	<Point X="182" Y="230" />
 	<Point X="182" Y="230" />
 	</Gesture>