<?xml version='1.0' encoding='utf8'?>
<Gesture Name="right_curly_brace3" Subject="2" Speed="Medium" Number="3" NumPts="176" Milliseconds="1024" AppName="Gestures" AppVersion="1.0.0.0" Date="Thursday, March 02, 2023" TimeOfDay="01:56:30 AM"><Point X="154" Y="122" T="1" />
 	<Point X="155" Y="122" T="1" />
 	<Point X="156" Y="122" T="1" />
 	<Point X="157" Y="123" T="1" />
 	<Point X="158" Y="123" T="1" />
 	<Point X="160" Y="123" T="1" />
 	<Point X="161" Y="124" T="1" />
 	<Point X="162" Y="124" T="1" />
 	<Point X="163" Y="125" T="1" />
 	<Point X="165" Y="127" T="1" />
 	<Point X="166" Y="127" T="1" />
 	<Point X="167" Y="127" T="1" />
 	<Point X="168" Y="127" T="1" />
 	<Point X="169" Y="127" T="1" />
 	<Point X="170" Y="127" T="1" />
 	<Point X="172" Y="127" T="1" />
 	<Point X="173" Y="127" T="1" />
 	<Point X="174" Y="127" T="1" />
 	<Point X="175" Y="127" T="1" />
 	<Point X="176" Y="127" T="1" />
 	<Point X="177" Y="128" T="1" />
 	<Point X="178" Y="128" T="1" />
 	<Point X="178" Y="129" T="1" />
 	<Point X="180" Y="130" T="1" />
 	<Point X="181" Y="130" T="1" />
 	<Point X="182" Y="131" T="1" />
 	<Point X="183" Y="133" T="1" />
 	<Point X="184" Y="135" T="1" />
 	<Point X="186" Y="138" T="1" />
 	<Point X="189" Y="143" T="1" />
 	<Point X="190" Y="148" T="1" />
 	<Point X="191" Y="154" T="1" />
 	<Point X="192" Y="158" T="1" />
 	<Point X="192" Y="161" T="1" />
 	<Point X="192" Y="163" T="1" />
 	<Point X="192" Y="165" T="1" />
 	<Point X="192" Y="167" T="1" />
 	<Point X="192" Y="168" T="1" />
 	<Point X="192" Y="169" T="1" />
 	<Point X="192" Y="170" T="1" />
 	<Point X="192" Y="171" T="1" />
 	<Point X="192" Y="172" T="1" />
 	<Point X="192" Y="173" T="1" />
 	<Point X="192" Y="174" T="1" />
 	<Point X="193" Y="175" T="1" />
 	<Point X="194" Y="175" T="1" />
 	<Point X="194" Y="178" T="1" />
 	<Point X="194" Y="179" T="1" />
 	<Point X="194" Y="181" T="1" />
 	<Point X="195" Y="183" T="1" />
 	<Point X="195" Y="185" T="1" />
 	<Point X="195" Y="186" T="1" />
 	<Point X="196" Y="188" T="1" />
 	<Point X="197" Y="190" T="1" />
 	<Point X="198" Y="191" T="1" />
 	<Point X="198" Y="192" T="1" />
 	<Point X="198" Y="194" T="1" />
 	<Point X="199" Y="195" T="1" />
 	<Point X="199" Y="196" T="1" />
 	<Point X="200" Y="198" T="1" />
 	<Point X="201" Y="199" T="1" />
 	<Point X="202" Y="201" T="1" />
 	<Point X="202" Y="202" T="1" />
 	<Point X="202" Y="203" T="1" />
 	<Point X="203" Y="204" T="1" />
 	<Point X="205" Y="207" T="1" />
 	<Point X="206" Y="208" T="1" />
 	<Point X="207" Y="210" T="1" />
 	<Point X="209" Y="212" T="1" />
 	<Point X="209" Y="215" T="1" />
 	<Point X="211" Y="216" T="1" />
 	<Point X="212" Y="219" T="1" />
 	<Point X="213" Y="220" T="1" />
 	<Point X="214" Y="222" T="1" />
 	<Point X="214" Y="223" T="1" />
 	<Point X="215" Y="224" T="1" />
 	<Point X="216" Y="226" T="1" />
 	<Point X="217" Y="227" T="1" />
 	<Point X="218" Y="227" T="1" />
 	<Point X="218" Y="228" T="1" />
 	<Point X="218" Y="229" T="1" />
 	<Point X="218" Y="230" T="1" />
 	<Point X="219" Y="230" T="1" />
 	<Point X="220" Y="231" T="1" />
 	<Point X="221" Y="231" T="1" />
 	<Point X="222" Y="232" T="1" />
 	<Point X="223" Y="232" T="1" />
 	<Point X="224" Y="232" T="1" />
 	<Point X="225" Y="232" T="1" />
 	<Point X="226" Y="232" T="1" />
 	<Point X="227" Y="232" T="1" />
 	<Point X="228" Y="232" T="1" />
 	<Point X="229" Y="232" T="1" />
 	<Point X="229" Y="233" T="1" />
 	<Point X="229" Y="235" T="1" />
 	<Point X="228" Y="235" T="1" />
 	<Point X="226" Y="236" T="1" />
 	<Point X="225" Y="238" T="1" />
 	<Point X="223" Y="239" T="1" />
 	<Point X="222" Y="240" T="1" />
 	<Point X="220" Y="242" T="1" />
 	<Point X="218" Y="243" T="1" />
 	<Point X="216" Y="244" T="1" />
 	<Point X="214" Y="247" T="1" />
 	<Point X="212" Y="249" T="1" />
 	<Point X="210" Y="251" T="1" />
 	<Point X="209" Y="253" T="1" />
 	<Point X="207" Y="255" T="1" />
 	<Point X="206" Y="256" T="1" />
 	<Point X="206" Y="257" T="1" />
 	<Point X="205" Y="259" T="1" />
 	<Point X="205" Y="261" T="1" />
 	<Point X="204" Y="262" T="1" />
 	<Point X="203" Y="263" T="1" />
 	<Point X="203" Y="265" T="1" />
 	<Point X="203" Y="266" T="1" />
 	<Point X="202" Y="267" T="1" />
 	<Point X="202" Y="268" T="1" />
 	<Point X="202" Y="269" T="1" />
 	<Point X="202" Y="271" T="1" />
 	<Point X="202" Y="274" T="1" />
 	<Point X="202" Y="275" T="1" />
 	<Point X="202" Y="278" T="1" />
 	<Point X="202" Y="281" T="1" />
 	<Point X="202" Y="284" T="1" />
 	<Point X="202" Y="287" T="1" />
 	<Point X="202" Y="291" T="1" />
 	<Point X="202" Y="293" T="1" />
 	<Point X="202" Y="296" T="1" />
 	<Point X="202" Y="298" T="1" />
 	<Point X="202" Y="299" T="1" />
 	<Point X="202" Y="302" T="1" />
 	<Point X="203" Y="304" T="1" />
 	<Point X="203" Y="307" T="1" />
 	<Point X="204" Y="310" T="1" />
 	<Point X="204" Y="312" T="1" />
 	<Point X="204" Y="315" T="1" />
 	<Point X="205" Y="319" T="1" />
 	<Point X="205" Y="322" T="1" />
 	<Point X="205" Y="325" T="1" />
 	<Point X="205" Y="327" T="1" />
 	<Point X="205" Y="330" T="1" />
 	<Point X="205" Y="331" T="1" />
 	<Point X="205" Y="334" T="1" />
 	<Point X="205" Y="335" T="1" />
 	<Point X="205" Y="336" T="1" />
 	<Point X="205" Y="337" T="1" />
 	<Point X="205" Y="339" T="1" />
 	<Point X="204" Y="339" T="1" />
 	<Point X="203" Y="339" T="1" />
 	<Point X="203" Y="340" T="1" />
 	<Point X="202" Y="340" T="1" />
 	<Point X="202" Y="341" T="1" />
 	<Point X="201" Y="342" T="1" />
 	<Point X="199" Y="343" T="1" />
 	<Point X="198" Y="343" T="1" />
 	<Point X="196" Y="344" T="1" />
 	<Point X="194" Y="344" T="1" />
 	<Point X="193" Y="345" T="1" />
 	<Point X="191" Y="345" T="1" />
 	<Point X="189" Y="345" T="1" />
 	<Point X="188" Y="345" T="1" />
 	<Point X="187" Y="345" T="1" />
 	<Point X="186" Y="345" T="1" />
 	<Point X="185" Y="345" T="1" />
 	<Point X="184" Y="345" T="1" />
 	<Point X="183" Y="345" T="1" />
 	<Point X="182" Y="345" T="1" />
 	<Point X="182" Y="346" T="1" />
 	<Point X="181" Y="346" T="1" />
 	<Point X="180" Y="346" T="1" />
 	<Point X="179" Y="346" T="1" />
 	<Point X="178" Y="346" T="1" />
 	<Point X="177" Y="346" T="1" />
 	<Point X="175" Y="346" T="1" />
 	<Point X="175" Y="346" T="1" />
 	<Point X="154" Y="122" T="1" />
 	<Point X="155" Y="122" T="1" />
 	<Point X="156" Y="122" T="1" />
 	<Point X="157" Y="123" T="1" />
 	<Point X="158" Y="123" T="1" />
 	<Point X="160" Y="123" T="1" />
 	<Point X="161" Y="124" T="1" />
 	<Point X="162" Y="124" T="1" />
 	<Point X="163" Y="125" T="1" />
 	<Point X="165" Y="127" T="1" />
 	<Point X="166" Y="127" T="1" />
 	<Point X="167" Y="127" T="1" />
 	<Point X="168" Y="127" T="1" />
 	<Point X="169" Y="127" T="1" />
 	<Point X="170" Y="127" T="1" />
 	<Point X="172" Y="127" T="1" />
 	<Point X="173" Y="127" T="1" />
 	<Point X="174" Y="127" T="1" />
 	<Point X="175" Y="127" T="1" />
 	<Point X="176" Y="127" T="1" />
 	<Point X="177" Y="128" T="1" />
 	<Point X="178" Y="128" T="1" />
 	<Point X="178" Y="129" T="1" />
 	<Point X="180" Y="130" T="1" />
 	<Point X="181" Y="130" T="1" />
 	<Point X="182" Y="131" T="1" />
 	<Point X="183" Y="133" T="1" />
 	<Point X="184" Y="135" T="1" />
 	<Point X="186" Y="138" T="1" />
 	<Point X="189" Y="143" T="1" />
 	<Point X="190" Y="148" T="1" />
 	<Point X="191" Y="154" T="1" />
 	<Point X="192" Y="158" T="1" />
 	<Point X="192" Y="161" T="1" />
 	<Point X="192" Y="163" T="1" />
 	<Point X="192" Y="165" T="1" />
 	<Point X="192" Y="167" T="1" />
 	<Point X="192" Y="168" T="1" />
 	<Point X="192" Y="169" T="1" />
 	<Point X="192" Y="170" T="1" />
 	<Point X="192" Y="171" T="1" />
 	<Point X="192" Y="172" T="1" />
 	<Point X="192" Y="173" T="1" />
 	<Point X="192" Y="174" T="1" />
 	<Point X="193" Y="175" T="1" />
 	<Point X="194" Y="175" T="1" />
 	<Point X="194" Y="178" T="1" />
 	<Point X="194" Y="179" T="1" />
 	<Point X="194" Y="181" T="1" />
 	<Point X="195" Y="183" T="1" />
 	<Point X="195" Y="185" T="1" />
 	<Point X="195" Y="186" T="1" />
 	<Point X="196" Y="188" T="1" />
 	<Point X="197" Y="190" T="1" />
 	<Point X="198" Y="191" T="1" />
 	<Point X="198" Y="192" T="1" />
 	<Point X="198" Y="194" T="1" />
 	<Point X="199" Y="195" T="1" />
 	<Point X="199" Y="196" T="1" />
 	<Point X="200" Y="198" T="1" />
 	<Point X="201" Y="199" T="1" />
 	<Point X="202" Y="201" T="1" />
 	<Point X="202" Y="202" T="1" />
 	<Point X="202" Y="203" T="1" />
 	<Point X="203" Y="204" T="1" />
 	<Point X="205" Y="207" T="1" />
 	<Point X="206" Y="208" T="1" />
 	<Point X="207" Y="210" T="1" />
 	<Point X="209" Y="212" T="1" />
 	<Point X="209" Y="215" T="1" />
 	<Point X="211" Y="216" T="1" />
 	<Point X="212" Y="219" T="1" />
 	<Point X="213" Y="220" T="1" />
 	<Point X="214" Y="222" T="1" />
 	<Point X="214" Y="223" T="1" />
 	<Point X="215" Y="224" T="1" />
 	<Point X="216" Y="226" T="1" />
 	<Point X="217" Y="227" T="1" />
 	<Point X="218" Y="227" T="1" />
 	<Point X="218" Y="228" T="1" />
 	<Point X="218" Y="229" T="1" />
 	<Point X="218" Y="230" T="1" />
 	<Point X="219" Y="230" T="1" />
 	<Point X="220" Y="231" T="1" />
 	<Point X="221" Y="231" T="1" />
 	<Point X="222" Y="232" T="1" />
 	<Point X="223" Y="232" T="1" />
 	<Point X="224" Y="232" T="1" />
 	<Point X="225" Y="232" T="1" />
 	<Point X="226" Y="232" T="1" />
 	<Point X="227" Y="232" T="1" />
 	<Point X="228" Y="232" T="1" />
 	<Point X="229" Y="232" T="1" />
 	<Point X="229" Y="233" T="1" />
 	<Point X="229" Y="235" T="1" />
 	<Point X="228" Y="235" T="1" />
 	<Point X="226" Y="236" T="1" />
 	<Point X="225" Y="238" T="1" />
 	<Point X="223" Y="239" T="1" />
 	<Point X="222" Y="240" T="1" />
 	<Point X="220" Y="242" T="1" />
 	<Point X="218" Y="243" T="1" />
 	<Point X="216" Y="244" T="1" />
 	<Point X="214" Y="247" T="1" />
 	<Point X="212" Y="249" T="1" />
 	<Point X="210" Y="251" T="1" />
 	<Point X="209" Y="253" T="1" />
 	<Point X="207" Y="255" T="1" />
 	<Point X="206" Y="256" T="1" />
 	<Point X="206" Y="257" T="1" />
 	<Point X="205" Y="259" T="1" />
 	<Point X="205" Y="261" T="1" />
 	<Point X="204" Y="262" T="1" />
 	<Point X="203" Y="263" T="1" />
 	<Point X="203" Y="265" T="1" />
 	<Point X="203" Y="266" T="1" />
 	<Point X="202" Y="267" T="1" />
 	<Point X="202" Y="268" T="1" />
 	<Point X="202" Y="269" T="1" />
 	<Point X="202" Y="271" T="1" />
 	<Point X="202" Y="274" T="1" />
 	<Point X="202" Y="275" T="1" />
 	<Point X="202" Y="278" T="1" />
 	<Point X="202" Y="281" T="1" />
 	<Point X="202" Y="284" T="1" />
 	<Point X="202" Y="287" T="1" />
 	<Point X="202" Y="291" T="1" />
 	<Point X="202" Y="293" T="1" />
 	<Point X="202" Y="296" T="1" />
 	<Point X="202" Y="298" T="1" />
 	<Point X="202" Y="299" T="1" />
 	<Point X="202" Y="302" T="1" />
 	<Point X="203" Y="304" T="1" />
 	<Point X="203" Y="307" T="1" />
 	<Point X="204" Y="310" T="1" />
 	<Point X="204" Y="312" T="1" />
 	<Point X="204" Y="315" T="1" />
 	<Point X="205" Y="319" T="1" />
 	<Point X="205" Y="322" T="1" />
 	<Point X="205" Y="325" T="1" />
 	<Point X="205" Y="327" T="1" />
 	<Point X="205" Y="330" T="1" />
 	<Point X="205" Y="331" T="1" />
 	<Point X="205" Y="334" T="1" />
 	<Point X="205" Y="335" T="1" />
 	<Point X="205" Y="336" T="1" />
 	<Point X="205" Y="337" T="1" />
 	<Point X="205" Y="339" T="1" />
 	<Point X="204" Y="339" T="1" />
 	<Point X="203" Y="339" T="1" />
 	<Point X="203" Y="340" T="1" />
 	<Point X="202" Y="340" T="1" />
 	<Point X="202" Y="341" T="1" />
 	<Point X="201" Y="342" T="1" />
 	<Point X="199" Y="343" T="1" />
 	<Point X="198" Y="343" T="1" />
 	<Point X="196" Y="344" T="1" />
 	<Point X="194" Y="344" T="1" />
 	<Point X="193" Y="345" T="1" />
 	<Point X="191" Y="345" T="1" />
 	<Point X="189" Y="345" T="1" />
 	<Point X="188" Y="345" T="1" />
 	<Point X="187" Y="345" T="1" />
 	<Point X="186" Y="345" T="1" />
 	<Point X="185" Y="345" T="1" />
 	<Point X="184" Y="345" T="1" />
 	<Point X="183" Y="345" T="1" />
 	<Point X="182" Y="345" T="1" />
 	<Point X="182" Y="346" T="1" />
 	<Point X="181" Y="346" T="1" />
 	<Point X="180" Y="346" T="1" />
 	<Point X="179" Y="346" T="1" />
 	<Point X="178" Y="346" T="1" />
 	<Point X="177" Y="346" T="1" />
 	<Point X="175" Y="346" T="1" />
 	<Point X="175" Y="346" T="1" />
 	</Gesture>