<?xml version='1.0' encoding='utf8'?>
<Gesture Name="36" Subject="1" Speed="Medium" Number="6" NumPts="91" AppName="Gestures" AppVersion="1.0.0.0" Date="Monday, April 17, 2023" TimeOfDay="00:19:52 AM"><Point X="205" Y="172" />
 	<Point X="205" Y="171" />
 	<Point X="206" Y="170" />
 	<Point X="208" Y="169" />
 	<Point X="212" Y="168" />
 	<Point X="215" Y="166" />
 	<Point X="217" Y="166" />
 	<Point X="221" Y="165" />
 	<Point X="223" Y="165" />
 	<Point X="225" Y="165" />
 	<Point X="227" Y="165" />
 	<Point X="228" Y="165" />
 	<Point X="230" Y="166" />
 	<Point X="230" Y="167" />
 	<Point X="231" Y="169" />
 	<Point X="231" Y="170" />
 	<Point X="232" Y="174" />
 	<Point X="233" Y="177" />
 	<Point X="233" Y="182" />
 	<Point X="234" Y="185" />
 	<Point X="234" Y="188" />
 	<Point X="234" Y="192" />
 	<Point X="234" Y="193" />
 	<Point X="234" Y="196" />
 	<Point X="233" Y="199" />
 	<Point X="233" Y="202" />
 	<Point X="232" Y="204" />
 	<Point X="231" Y="207" />
 	<Point X="231" Y="210" />
 	<Point X="229" Y="213" />
 	<Point X="228" Y="215" />
 	<Point X="227" Y="216" />
 	<Point X="225" Y="219" />
 	<Point X="222" Y="223" />
 	<Point X="221" Y="224" />
 	<Point X="218" Y="227" />
 	<Point X="217" Y="228" />
 	<Point X="215" Y="229" />
 	<Point X="214" Y="229" />
 	<Point X="213" Y="230" />
 	<Point X="211" Y="231" />
 	<Point X="210" Y="231" />
 	<Point X="209" Y="232" />
 	<Point X="208" Y="232" />
 	<Point X="207" Y="232" />
 	<Point X="207" Y="233" />
 	<Point X="207" Y="232" />
 	<Point X="208" Y="232" />
 	<Point X="211" Y="231" />
 	<Point X="214" Y="231" />
 	<Point X="218" Y="231" />
 	<Point X="222" Y="231" />
 	<Point X="227" Y="232" />
 	<Point X="230" Y="233" />
 	<Point X="234" Y="234" />
 	<Point X="236" Y="235" />
 	<Point X="237" Y="236" />
 	<Point X="237" Y="237" />
 	<Point X="238" Y="238" />
 	<Point X="238" Y="240" />
 	<Point X="239" Y="241" />
 	<Point X="239" Y="242" />
 	<Point X="239" Y="244" />
 	<Point X="239" Y="247" />
 	<Point X="239" Y="248" />
 	<Point X="239" Y="249" />
 	<Point X="239" Y="252" />
 	<Point X="239" Y="255" />
 	<Point X="239" Y="256" />
 	<Point X="239" Y="258" />
 	<Point X="238" Y="259" />
 	<Point X="238" Y="261" />
 	<Point X="236" Y="263" />
 	<Point X="235" Y="264" />
 	<Point X="234" Y="266" />
 	<Point X="232" Y="268" />
 	<Point X="230" Y="269" />
 	<Point X="226" Y="271" />
 	<Point X="223" Y="273" />
 	<Point X="219" Y="274" />
 	<Point X="215" Y="276" />
 	<Point X="212" Y="277" />
 	<Point X="211" Y="278" />
 	<Point X="209" Y="279" />
 	<Point X="207" Y="279" />
 	<Point X="206" Y="279" />
 	<Point X="205" Y="279" />
 	<Point X="204" Y="279" />
 	<Point X="204" Y="280" />
 	<Point X="204" Y="279" />
 	<Point X="204" Y="279" />
 	</Gesture>