<?xml version='1.0' encoding='utf8'?>
<Gesture Name="star1" Subject="11" Speed="Medium" Number="1" NumPts="32" Milliseconds="1024" AppName="Gestures" AppVersion="1.0.0.0" Date="Monday, March 06, 2023" TimeOfDay="17:53:53 PM"><Point X="403" Y="352" T="2023-03-06 17:53:47.913269" />
 	<Point X="396" Y="351" T="2023-03-06 17:53:47.919249" />
 	<Point X="388" Y="351" T="2023-03-06 17:53:47.926249" />
 	<Point X="381" Y="351" T="2023-03-06 17:53:47.933247" />
 	<Point X="374" Y="351" T="2023-03-06 17:53:47.940249" />
 	<Point X="368" Y="351" T="2023-03-06 17:53:47.948248" />
 	<Point X="361" Y="351" T="2023-03-06 17:53:47.954247" />
 	<Point X="353" Y="351" T="2023-03-06 17:53:47.962258" />
 	<Point X="347" Y="351" T="2023-03-06 17:53:47.969248" />
 	<Point X="340" Y="351" T="2023-03-06 17:53:47.976248" />
 	<Point X="332" Y="351" T="2023-03-06 17:53:47.983247" />
 	<Point X="324" Y="351" T="2023-03-06 17:53:47.990248" />
 	<Point X="318" Y="352" T="2023-03-06 17:53:47.998248" />
 	<Point X="310" Y="353" T="2023-03-06 17:53:48.005248" />
 	<Point X="303" Y="355" T="2023-03-06 17:53:48.013259" />
 	<Point X="294" Y="357" T="2023-03-06 17:53:48.019248" />
 	<Point X="285" Y="361" T="2023-03-06 17:53:48.026248" />
 	<Point X="276" Y="363" T="2023-03-06 17:53:48.033249" />
 	<Point X="270" Y="366" T="2023-03-06 17:53:48.040298" />
 	<Point X="262" Y="372" T="2023-03-06 17:53:48.047263" />
 	<Point X="254" Y="378" T="2023-03-06 17:53:48.054247" />
 	<Point X="246" Y="383" T="2023-03-06 17:53:48.062264" />
 	<Point X="237" Y="389" T="2023-03-06 17:53:48.069248" />
 	<Point X="228" Y="396" T="2023-03-06 17:53:48.076249" />
 	<Point X="220" Y="400" T="2023-03-06 17:53:48.083249" />
 	<Point X="214" Y="404" T="2023-03-06 17:53:48.090249" />
 	<Point X="209" Y="407" T="2023-03-06 17:53:48.097271" />
 	<Point X="204" Y="410" T="2023-03-06 17:53:48.104258" />
 	<Point X="200" Y="414" T="2023-03-06 17:53:48.113257" />
 	<Point X="195" Y="417" T="2023-03-06 17:53:48.119249" />
 	<Point X="189" Y="422" T="2023-03-06 17:53:48.126252" />
 	<Point X="189" Y="422" T="2023-03-06 17:53:48.134249" />
 	</Gesture>