<?xml version='1.0' encoding='utf8'?>
<Gesture Name="check100" Subject="6" Speed="Medium" Number="10" NumPts="39" Milliseconds="1024" AppName="Gestures" AppVersion="1.0.0.0" Date="Thursday, March 02, 2023" TimeOfDay="13:56:30 PM"><Point X="139" Y="214" T="1" />
 	<Point X="140" Y="216" T="1" />
 	<Point X="142" Y="219" T="1" />
 	<Point X="144" Y="223" T="1" />
 	<Point X="145" Y="226" T="1" />
 	<Point X="148" Y="233" T="1" />
 	<Point X="150" Y="238" T="1" />
 	<Point X="153" Y="243" T="1" />
 	<Point X="153" Y="244" T="1" />
 	<Point X="156" Y="250" T="1" />
 	<Point X="157" Y="252" T="1" />
 	<Point X="158" Y="253" T="1" />
 	<Point X="159" Y="254" T="1" />
 	<Point X="160" Y="255" T="1" />
 	<Point X="161" Y="255" T="1" />
 	<Point X="162" Y="255" T="1" />
 	<Point X="164" Y="255" T="1" />
 	<Point X="169" Y="254" T="1" />
 	<Point X="174" Y="252" T="1" />
 	<Point X="183" Y="248" T="1" />
 	<Point X="189" Y="245" T="1" />
 	<Point X="200" Y="240" T="1" />
 	<Point X="219" Y="231" T="1" />
 	<Point X="229" Y="226" T="1" />
 	<Point X="244" Y="217" T="1" />
 	<Point X="250" Y="214" T="1" />
 	<Point X="267" Y="202" T="1" />
 	<Point X="279" Y="194" T="1" />
 	<Point X="292" Y="184" T="1" />
 	<Point X="306" Y="174" T="1" />
 	<Point X="321" Y="164" T="1" />
 	<Point X="340" Y="152" T="1" />
 	<Point X="351" Y="146" T="1" />
 	<Point X="360" Y="141" T="1" />
 	<Point X="372" Y="136" T="1" />
 	<Point X="377" Y="134" T="1" />
 	<Point X="380" Y="132" T="1" />
 	<Point X="381" Y="132" T="1" />
 	<Point X="381" Y="132" T="1" />
 	</Gesture>