<?xml version='1.0' encoding='utf8'?>
<Gesture Name="circle4" Subject="6" Speed="Medium" Number="4" NumPts="93" Milliseconds="1024" AppName="Gestures" AppVersion="1.0.0.0" Date="Thursday, March 02, 2023" TimeOfDay="13:56:30 PM"><Point X="212" Y="194" T="1" />
 	<Point X="211" Y="194" T="1" />
 	<Point X="210" Y="194" T="1" />
 	<Point X="209" Y="194" T="1" />
 	<Point X="209" Y="195" T="1" />
 	<Point X="208" Y="195" T="1" />
 	<Point X="207" Y="196" T="1" />
 	<Point X="205" Y="198" T="1" />
 	<Point X="204" Y="200" T="1" />
 	<Point X="203" Y="201" T="1" />
 	<Point X="200" Y="205" T="1" />
 	<Point X="198" Y="214" T="1" />
 	<Point X="196" Y="219" T="1" />
 	<Point X="195" Y="228" T="1" />
 	<Point X="195" Y="234" T="1" />
 	<Point X="194" Y="240" T="1" />
 	<Point X="194" Y="245" T="1" />
 	<Point X="194" Y="253" T="1" />
 	<Point X="195" Y="258" T="1" />
 	<Point X="197" Y="263" T="1" />
 	<Point X="200" Y="267" T="1" />
 	<Point X="201" Y="271" T="1" />
 	<Point X="202" Y="272" T="1" />
 	<Point X="205" Y="275" T="1" />
 	<Point X="206" Y="276" T="1" />
 	<Point X="210" Y="277" T="1" />
 	<Point X="211" Y="278" T="1" />
 	<Point X="215" Y="280" T="1" />
 	<Point X="220" Y="281" T="1" />
 	<Point X="223" Y="281" T="1" />
 	<Point X="228" Y="284" T="1" />
 	<Point X="230" Y="284" T="1" />
 	<Point X="235" Y="285" T="1" />
 	<Point X="243" Y="286" T="1" />
 	<Point X="248" Y="286" T="1" />
 	<Point X="252" Y="287" T="1" />
 	<Point X="255" Y="287" T="1" />
 	<Point X="258" Y="287" T="1" />
 	<Point X="259" Y="287" T="1" />
 	<Point X="259" Y="286" T="1" />
 	<Point X="260" Y="286" T="1" />
 	<Point X="260" Y="285" T="1" />
 	<Point X="261" Y="284" T="1" />
 	<Point X="261" Y="283" T="1" />
 	<Point X="262" Y="280" T="1" />
 	<Point X="263" Y="276" T="1" />
 	<Point X="264" Y="273" T="1" />
 	<Point X="264" Y="271" T="1" />
 	<Point X="265" Y="270" T="1" />
 	<Point X="265" Y="266" T="1" />
 	<Point X="265" Y="265" T="1" />
 	<Point X="265" Y="262" T="1" />
 	<Point X="265" Y="258" T="1" />
 	<Point X="265" Y="255" T="1" />
 	<Point X="265" Y="252" T="1" />
 	<Point X="265" Y="248" T="1" />
 	<Point X="264" Y="247" T="1" />
 	<Point X="262" Y="243" T="1" />
 	<Point X="262" Y="240" T="1" />
 	<Point X="260" Y="237" T="1" />
 	<Point X="259" Y="235" T="1" />
 	<Point X="257" Y="232" T="1" />
 	<Point X="256" Y="229" T="1" />
 	<Point X="255" Y="227" T="1" />
 	<Point X="253" Y="224" T="1" />
 	<Point X="251" Y="220" T="1" />
 	<Point X="248" Y="216" T="1" />
 	<Point X="247" Y="215" T="1" />
 	<Point X="244" Y="211" T="1" />
 	<Point X="243" Y="210" T="1" />
 	<Point X="243" Y="209" T="1" />
 	<Point X="241" Y="208" T="1" />
 	<Point X="239" Y="207" T="1" />
 	<Point X="238" Y="206" T="1" />
 	<Point X="234" Y="203" T="1" />
 	<Point X="231" Y="201" T="1" />
 	<Point X="226" Y="198" T="1" />
 	<Point X="225" Y="197" T="1" />
 	<Point X="224" Y="197" T="1" />
 	<Point X="223" Y="196" T="1" />
 	<Point X="222" Y="196" T="1" />
 	<Point X="220" Y="195" T="1" />
 	<Point X="219" Y="195" T="1" />
 	<Point X="218" Y="195" T="1" />
 	<Point X="217" Y="195" T="1" />
 	<Point X="216" Y="195" T="1" />
 	<Point X="215" Y="195" T="1" />
 	<Point X="214" Y="195" T="1" />
 	<Point X="213" Y="195" T="1" />
 	<Point X="212" Y="195" T="1" />
 	<Point X="211" Y="195" T="1" />
 	<Point X="210" Y="196" T="1" />
 	<Point X="210" Y="196" T="1" />
 	<Point X="212" Y="194" T="1" />
 	<Point X="211" Y="194" T="1" />
 	<Point X="210" Y="194" T="1" />
 	<Point X="209" Y="194" T="1" />
 	<Point X="209" Y="195" T="1" />
 	<Point X="208" Y="195" T="1" />
 	<Point X="207" Y="196" T="1" />
 	<Point X="205" Y="198" T="1" />
 	<Point X="204" Y="200" T="1" />
 	<Point X="203" Y="201" T="1" />
 	<Point X="200" Y="205" T="1" />
 	<Point X="198" Y="214" T="1" />
 	<Point X="196" Y="219" T="1" />
 	<Point X="195" Y="228" T="1" />
 	<Point X="195" Y="234" T="1" />
 	<Point X="194" Y="240" T="1" />
 	<Point X="194" Y="245" T="1" />
 	<Point X="194" Y="253" T="1" />
 	<Point X="195" Y="258" T="1" />
 	<Point X="197" Y="263" T="1" />
 	<Point X="200" Y="267" T="1" />
 	<Point X="201" Y="271" T="1" />
 	<Point X="202" Y="272" T="1" />
 	<Point X="205" Y="275" T="1" />
 	<Point X="206" Y="276" T="1" />
 	<Point X="210" Y="277" T="1" />
 	<Point X="211" Y="278" T="1" />
 	<Point X="215" Y="280" T="1" />
 	<Point X="220" Y="281" T="1" />
 	<Point X="223" Y="281" T="1" />
 	<Point X="228" Y="284" T="1" />
 	<Point X="230" Y="284" T="1" />
 	<Point X="235" Y="285" T="1" />
 	<Point X="243" Y="286" T="1" />
 	<Point X="248" Y="286" T="1" />
 	<Point X="252" Y="287" T="1" />
 	<Point X="255" Y="287" T="1" />
 	<Point X="258" Y="287" T="1" />
 	<Point X="259" Y="287" T="1" />
 	<Point X="259" Y="286" T="1" />
 	<Point X="260" Y="286" T="1" />
 	<Point X="260" Y="285" T="1" />
 	<Point X="261" Y="284" T="1" />
 	<Point X="261" Y="283" T="1" />
 	<Point X="262" Y="280" T="1" />
 	<Point X="263" Y="276" T="1" />
 	<Point X="264" Y="273" T="1" />
 	<Point X="264" Y="271" T="1" />
 	<Point X="265" Y="270" T="1" />
 	<Point X="265" Y="266" T="1" />
 	<Point X="265" Y="265" T="1" />
 	<Point X="265" Y="262" T="1" />
 	<Point X="265" Y="258" T="1" />
 	<Point X="265" Y="255" T="1" />
 	<Point X="265" Y="252" T="1" />
 	<Point X="265" Y="248" T="1" />
 	<Point X="264" Y="247" T="1" />
 	<Point X="262" Y="243" T="1" />
 	<Point X="262" Y="240" T="1" />
 	<Point X="260" Y="237" T="1" />
 	<Point X="259" Y="235" T="1" />
 	<Point X="257" Y="232" T="1" />
 	<Point X="256" Y="229" T="1" />
 	<Point X="255" Y="227" T="1" />
 	<Point X="253" Y="224" T="1" />
 	<Point X="251" Y="220" T="1" />
 	<Point X="248" Y="216" T="1" />
 	<Point X="247" Y="215" T="1" />
 	<Point X="244" Y="211" T="1" />
 	<Point X="243" Y="210" T="1" />
 	<Point X="243" Y="209" T="1" />
 	<Point X="241" Y="208" T="1" />
 	<Point X="239" Y="207" T="1" />
 	<Point X="238" Y="206" T="1" />
 	<Point X="234" Y="203" T="1" />
 	<Point X="231" Y="201" T="1" />
 	<Point X="226" Y="198" T="1" />
 	<Point X="225" Y="197" T="1" />
 	<Point X="224" Y="197" T="1" />
 	<Point X="223" Y="196" T="1" />
 	<Point X="222" Y="196" T="1" />
 	<Point X="220" Y="195" T="1" />
 	<Point X="219" Y="195" T="1" />
 	<Point X="218" Y="195" T="1" />
 	<Point X="217" Y="195" T="1" />
 	<Point X="216" Y="195" T="1" />
 	<Point X="215" Y="195" T="1" />
 	<Point X="214" Y="195" T="1" />
 	<Point X="213" Y="195" T="1" />
 	<Point X="212" Y="195" T="1" />
 	<Point X="211" Y="195" T="1" />
 	<Point X="210" Y="196" T="1" />
 	<Point X="210" Y="196" T="1" />
 	</Gesture>