<?xml version='1.0' encoding='utf8'?>
<Gesture Name="circle02" Subject="6" Speed="Medium" Number="2" NumPts="125" Milliseconds="1024" AppName="Gestures" AppVersion="1.0.0.0" Date="Thursday, March 02, 2023" TimeOfDay="13:56:30 PM"><Point X="163" Y="162" T="1" />
 	<Point X="162" Y="163" T="1" />
 	<Point X="161" Y="163" T="1" />
 	<Point X="157" Y="168" T="1" />
 	<Point X="154" Y="172" T="1" />
 	<Point X="153" Y="173" T="1" />
 	<Point X="148" Y="177" T="1" />
 	<Point X="145" Y="181" T="1" />
 	<Point X="139" Y="188" T="1" />
 	<Point X="136" Y="194" T="1" />
 	<Point X="134" Y="199" T="1" />
 	<Point X="131" Y="205" T="1" />
 	<Point X="130" Y="209" T="1" />
 	<Point X="127" Y="217" T="1" />
 	<Point X="125" Y="224" T="1" />
 	<Point X="124" Y="231" T="1" />
 	<Point X="121" Y="243" T="1" />
 	<Point X="121" Y="250" T="1" />
 	<Point X="121" Y="255" T="1" />
 	<Point X="121" Y="262" T="1" />
 	<Point X="121" Y="269" T="1" />
 	<Point X="123" Y="275" T="1" />
 	<Point X="124" Y="281" T="1" />
 	<Point X="128" Y="289" T="1" />
 	<Point X="131" Y="296" T="1" />
 	<Point X="134" Y="301" T="1" />
 	<Point X="139" Y="308" T="1" />
 	<Point X="145" Y="313" T="1" />
 	<Point X="150" Y="316" T="1" />
 	<Point X="157" Y="322" T="1" />
 	<Point X="163" Y="325" T="1" />
 	<Point X="172" Y="332" T="1" />
 	<Point X="180" Y="335" T="1" />
 	<Point X="185" Y="337" T="1" />
 	<Point X="189" Y="339" T="1" />
 	<Point X="199" Y="339" T="1" />
 	<Point X="206" Y="339" T="1" />
 	<Point X="211" Y="339" T="1" />
 	<Point X="219" Y="339" T="1" />
 	<Point X="230" Y="338" T="1" />
 	<Point X="235" Y="336" T="1" />
 	<Point X="238" Y="335" T="1" />
 	<Point X="245" Y="334" T="1" />
 	<Point X="245" Y="333" T="1" />
 	<Point X="246" Y="333" T="1" />
 	<Point X="248" Y="330" T="1" />
 	<Point X="249" Y="330" T="1" />
 	<Point X="252" Y="326" T="1" />
 	<Point X="254" Y="322" T="1" />
 	<Point X="257" Y="317" T="1" />
 	<Point X="260" Y="310" T="1" />
 	<Point X="261" Y="309" T="1" />
 	<Point X="267" Y="300" T="1" />
 	<Point X="268" Y="297" T="1" />
 	<Point X="273" Y="289" T="1" />
 	<Point X="277" Y="279" T="1" />
 	<Point X="278" Y="276" T="1" />
 	<Point X="280" Y="269" T="1" />
 	<Point X="282" Y="264" T="1" />
 	<Point X="283" Y="257" T="1" />
 	<Point X="284" Y="253" T="1" />
 	<Point X="285" Y="250" T="1" />
 	<Point X="285" Y="249" T="1" />
 	<Point X="285" Y="245" T="1" />
 	<Point X="285" Y="242" T="1" />
 	<Point X="285" Y="240" T="1" />
 	<Point X="285" Y="239" T="1" />
 	<Point X="285" Y="235" T="1" />
 	<Point X="284" Y="234" T="1" />
 	<Point X="284" Y="232" T="1" />
 	<Point X="283" Y="232" T="1" />
 	<Point X="282" Y="228" T="1" />
 	<Point X="278" Y="223" T="1" />
 	<Point X="277" Y="220" T="1" />
 	<Point X="272" Y="214" T="1" />
 	<Point X="270" Y="212" T="1" />
 	<Point X="266" Y="208" T="1" />
 	<Point X="261" Y="202" T="1" />
 	<Point X="257" Y="199" T="1" />
 	<Point X="255" Y="196" T="1" />
 	<Point X="251" Y="192" T="1" />
 	<Point X="250" Y="192" T="1" />
 	<Point X="246" Y="189" T="1" />
 	<Point X="243" Y="186" T="1" />
 	<Point X="242" Y="185" T="1" />
 	<Point X="240" Y="184" T="1" />
 	<Point X="238" Y="182" T="1" />
 	<Point X="234" Y="180" T="1" />
 	<Point X="233" Y="179" T="1" />
 	<Point X="229" Y="177" T="1" />
 	<Point X="226" Y="176" T="1" />
 	<Point X="225" Y="174" T="1" />
 	<Point X="224" Y="174" T="1" />
 	<Point X="221" Y="172" T="1" />
 	<Point X="217" Y="172" T="1" />
 	<Point X="214" Y="172" T="1" />
 	<Point X="212" Y="171" T="1" />
 	<Point X="211" Y="171" T="1" />
 	<Point X="210" Y="171" T="1" />
 	<Point X="209" Y="171" T="1" />
 	<Point X="208" Y="171" T="1" />
 	<Point X="206" Y="171" T="1" />
 	<Point X="205" Y="171" T="1" />
 	<Point X="203" Y="172" T="1" />
 	<Point X="202" Y="173" T="1" />
 	<Point X="200" Y="173" T="1" />
 	<Point X="199" Y="173" T="1" />
 	<Point X="199" Y="174" T="1" />
 	<Point X="197" Y="174" T="1" />
 	<Point X="196" Y="174" T="1" />
 	<Point X="195" Y="175" T="1" />
 	<Point X="193" Y="175" T="1" />
 	<Point X="192" Y="176" T="1" />
 	<Point X="190" Y="176" T="1" />
 	<Point X="187" Y="177" T="1" />
 	<Point X="184" Y="177" T="1" />
 	<Point X="180" Y="178" T="1" />
 	<Point X="178" Y="178" T="1" />
 	<Point X="177" Y="178" T="1" />
 	<Point X="176" Y="179" T="1" />
 	<Point X="175" Y="179" T="1" />
 	<Point X="174" Y="179" T="1" />
 	<Point X="173" Y="179" T="1" />
 	<Point X="172" Y="179" T="1" />
 	<Point X="172" Y="179" T="1" />
 	</Gesture>