<?xml version='1.0' encoding='utf8'?>
<Gesture Name="zig zag10" Subject="6" Speed="Medium" Number="10" NumPts="89" AppName="Gestures" AppVersion="1.0.0.0" Date="Thursday, March 02, 2023" TimeOfDay="13:56:30 PM"><Point X="101" Y="262" />
 	<Point X="101" Y="260" />
 	<Point X="102" Y="257" />
 	<Point X="103" Y="254" />
 	<Point X="105" Y="249" />
 	<Point X="110" Y="240" />
 	<Point X="114" Y="235" />
 	<Point X="115" Y="233" />
 	<Point X="118" Y="226" />
 	<Point X="121" Y="219" />
 	<Point X="128" Y="212" />
 	<Point X="132" Y="205" />
 	<Point X="134" Y="201" />
 	<Point X="138" Y="198" />
 	<Point X="141" Y="196" />
 	<Point X="144" Y="194" />
 	<Point X="145" Y="194" />
 	<Point X="146" Y="195" />
 	<Point X="149" Y="200" />
 	<Point X="152" Y="207" />
 	<Point X="155" Y="212" />
 	<Point X="159" Y="221" />
 	<Point X="161" Y="226" />
 	<Point X="168" Y="240" />
 	<Point X="170" Y="243" />
 	<Point X="176" Y="254" />
 	<Point X="182" Y="260" />
 	<Point X="188" Y="266" />
 	<Point X="193" Y="270" />
 	<Point X="195" Y="273" />
 	<Point X="198" Y="275" />
 	<Point X="199" Y="275" />
 	<Point X="200" Y="275" />
 	<Point X="201" Y="275" />
 	<Point X="202" Y="275" />
 	<Point X="203" Y="274" />
 	<Point X="206" Y="271" />
 	<Point X="211" Y="264" />
 	<Point X="215" Y="256" />
 	<Point X="218" Y="252" />
 	<Point X="224" Y="243" />
 	<Point X="229" Y="236" />
 	<Point X="234" Y="227" />
 	<Point X="238" Y="221" />
 	<Point X="243" Y="215" />
 	<Point X="245" Y="213" />
 	<Point X="248" Y="211" />
 	<Point X="248" Y="210" />
 	<Point X="249" Y="210" />
 	<Point X="250" Y="209" />
 	<Point X="251" Y="210" />
 	<Point X="251" Y="211" />
 	<Point X="255" Y="218" />
 	<Point X="259" Y="228" />
 	<Point X="262" Y="237" />
 	<Point X="268" Y="256" />
 	<Point X="272" Y="270" />
 	<Point X="278" Y="283" />
 	<Point X="283" Y="295" />
 	<Point X="288" Y="301" />
 	<Point X="294" Y="308" />
 	<Point X="298" Y="314" />
 	<Point X="300" Y="315" />
 	<Point X="305" Y="317" />
 	<Point X="308" Y="318" />
 	<Point X="310" Y="318" />
 	<Point X="312" Y="318" />
 	<Point X="315" Y="315" />
 	<Point X="317" Y="313" />
 	<Point X="322" Y="307" />
 	<Point X="328" Y="298" />
 	<Point X="335" Y="289" />
 	<Point X="341" Y="280" />
 	<Point X="346" Y="273" />
 	<Point X="351" Y="265" />
 	<Point X="358" Y="254" />
 	<Point X="363" Y="245" />
 	<Point X="369" Y="238" />
 	<Point X="370" Y="237" />
 	<Point X="373" Y="232" />
 	<Point X="374" Y="231" />
 	<Point X="376" Y="228" />
 	<Point X="377" Y="227" />
 	<Point X="377" Y="226" />
 	<Point X="378" Y="225" />
 	<Point X="378" Y="224" />
 	<Point X="379" Y="223" />
 	<Point X="379" Y="222" />
 	<Point X="379" Y="222" />
 	</Gesture>