<?xml version='1.0' encoding='utf8'?>
<Gesture Name="Seven09" Subject="4" Speed="Medium" Number="9" NumPts="87" Milliseconds="1024" AppName="Gestures" AppVersion="1.0.0.0" Date="Monday, April 17, 2023" TimeOfDay="06:32:33 AM"><Point X="191" Y="270" T="1" />
 	<Point X="196" Y="270" T="1" />
 	<Point X="201" Y="270" T="1" />
 	<Point X="208" Y="270" T="1" />
 	<Point X="212" Y="270" T="1" />
 	<Point X="215" Y="270" T="1" />
 	<Point X="219" Y="270" T="1" />
 	<Point X="220" Y="270" T="1" />
 	<Point X="221" Y="270" T="1" />
 	<Point X="224" Y="270" T="1" />
 	<Point X="225" Y="270" T="1" />
 	<Point X="227" Y="270" T="1" />
 	<Point X="228" Y="270" T="1" />
 	<Point X="230" Y="270" T="1" />
 	<Point X="231" Y="270" T="1" />
 	<Point X="232" Y="270" T="1" />
 	<Point X="233" Y="270" T="1" />
 	<Point X="235" Y="270" T="1" />
 	<Point X="236" Y="270" T="1" />
 	<Point X="238" Y="270" T="1" />
 	<Point X="239" Y="270" T="1" />
 	<Point X="240" Y="270" T="1" />
 	<Point X="241" Y="270" T="1" />
 	<Point X="242" Y="270" T="1" />
 	<Point X="243" Y="270" T="1" />
 	<Point X="244" Y="270" T="1" />
 	<Point X="245" Y="270" T="1" />
 	<Point X="246" Y="270" T="1" />
 	<Point X="247" Y="270" T="1" />
 	<Point X="248" Y="270" T="1" />
 	<Point X="249" Y="270" T="1" />
 	<Point X="250" Y="270" T="1" />
 	<Point X="251" Y="270" T="1" />
 	<Point X="252" Y="270" T="1" />
 	<Point X="254" Y="270" T="1" />
 	<Point X="255" Y="270" T="1" />
 	<Point X="256" Y="270" T="1" />
 	<Point X="257" Y="269" T="1" />
 	<Point X="258" Y="269" T="1" />
 	<Point X="259" Y="269" T="1" />
 	<Point X="260" Y="269" T="1" />
 	<Point X="260" Y="270" T="1" />
 	<Point X="260" Y="272" T="1" />
 	<Point X="260" Y="274" T="1" />
 	<Point X="258" Y="276" T="1" />
 	<Point X="256" Y="279" T="1" />
 	<Point X="255" Y="282" T="1" />
 	<Point X="253" Y="286" T="1" />
 	<Point X="251" Y="290" T="1" />
 	<Point X="249" Y="296" T="1" />
 	<Point X="248" Y="302" T="1" />
 	<Point X="246" Y="306" T="1" />
 	<Point X="244" Y="311" T="1" />
 	<Point X="242" Y="314" T="1" />
 	<Point X="240" Y="317" T="1" />
 	<Point X="239" Y="320" T="1" />
 	<Point X="236" Y="325" T="1" />
 	<Point X="234" Y="327" T="1" />
 	<Point X="232" Y="332" T="1" />
 	<Point X="228" Y="336" T="1" />
 	<Point X="227" Y="342" T="1" />
 	<Point X="225" Y="344" T="1" />
 	<Point X="223" Y="349" T="1" />
 	<Point X="221" Y="352" T="1" />
 	<Point X="220" Y="355" T="1" />
 	<Point X="218" Y="357" T="1" />
 	<Point X="218" Y="359" T="1" />
 	<Point X="216" Y="362" T="1" />
 	<Point X="216" Y="363" T="1" />
 	<Point X="214" Y="366" T="1" />
 	<Point X="213" Y="369" T="1" />
 	<Point X="212" Y="371" T="1" />
 	<Point X="212" Y="374" T="1" />
 	<Point X="211" Y="376" T="1" />
 	<Point X="210" Y="378" T="1" />
 	<Point X="209" Y="380" T="1" />
 	<Point X="208" Y="382" T="1" />
 	<Point X="208" Y="384" T="1" />
 	<Point X="208" Y="385" T="1" />
 	<Point X="208" Y="386" T="1" />
 	<Point X="208" Y="387" T="1" />
 	<Point X="208" Y="388" T="1" />
 	<Point X="207" Y="389" T="1" />
 	<Point X="207" Y="390" T="1" />
 	<Point X="206" Y="390" T="1" />
 	<Point X="205" Y="390" T="1" />
 	<Point X="205" Y="390" T="1" />
 	</Gesture>