<?xml version='1.0' encoding='utf8'?>
<Gesture Name="Four01" Subject="2" Speed="Medium" Number="1" NumPts="65" Milliseconds="1024" AppName="Gestures" AppVersion="1.0.0.0" Date="Monday, April 17, 2023" TimeOfDay="00:36:14 AM"><Point X="275" Y="333" T="1" />
 	<Point X="275" Y="331" T="1" />
 	<Point X="275" Y="330" T="1" />
 	<Point X="275" Y="327" T="1" />
 	<Point X="276" Y="323" T="1" />
 	<Point X="276" Y="317" T="1" />
 	<Point X="276" Y="313" T="1" />
 	<Point X="277" Y="306" T="1" />
 	<Point X="279" Y="297" T="1" />
 	<Point X="280" Y="286" T="1" />
 	<Point X="281" Y="277" T="1" />
 	<Point X="282" Y="268" T="1" />
 	<Point X="282" Y="262" T="1" />
 	<Point X="283" Y="255" T="1" />
 	<Point X="284" Y="246" T="1" />
 	<Point X="284" Y="240" T="1" />
 	<Point X="285" Y="231" T="1" />
 	<Point X="285" Y="226" T="1" />
 	<Point X="285" Y="220" T="1" />
 	<Point X="287" Y="211" T="1" />
 	<Point X="287" Y="207" T="1" />
 	<Point X="287" Y="204" T="1" />
 	<Point X="287" Y="203" T="1" />
 	<Point X="287" Y="199" T="1" />
 	<Point X="287" Y="197" T="1" />
 	<Point X="287" Y="193" T="1" />
 	<Point X="287" Y="190" T="1" />
 	<Point X="287" Y="188" T="1" />
 	<Point X="287" Y="186" T="1" />
 	<Point X="287" Y="185" T="1" />
 	<Point X="287" Y="184" T="1" />
 	<Point X="286" Y="186" T="1" />
 	<Point X="284" Y="190" T="1" />
 	<Point X="279" Y="198" T="1" />
 	<Point X="274" Y="206" T="1" />
 	<Point X="258" Y="223" T="1" />
 	<Point X="250" Y="234" T="1" />
 	<Point X="235" Y="247" T="1" />
 	<Point X="224" Y="259" T="1" />
 	<Point X="214" Y="270" T="1" />
 	<Point X="200" Y="284" T="1" />
 	<Point X="192" Y="293" T="1" />
 	<Point X="185" Y="300" T="1" />
 	<Point X="180" Y="308" T="1" />
 	<Point X="175" Y="314" T="1" />
 	<Point X="174" Y="316" T="1" />
 	<Point X="174" Y="317" T="1" />
 	<Point X="173" Y="318" T="1" />
 	<Point X="173" Y="319" T="1" />
 	<Point X="174" Y="319" T="1" />
 	<Point X="175" Y="318" T="1" />
 	<Point X="177" Y="318" T="1" />
 	<Point X="182" Y="315" T="1" />
 	<Point X="196" Y="309" T="1" />
 	<Point X="218" Y="303" T="1" />
 	<Point X="264" Y="290" T="1" />
 	<Point X="310" Y="278" T="1" />
 	<Point X="361" Y="265" T="1" />
 	<Point X="395" Y="255" T="1" />
 	<Point X="441" Y="243" T="1" />
 	<Point X="454" Y="238" T="1" />
 	<Point X="472" Y="230" T="1" />
 	<Point X="476" Y="228" T="1" />
 	<Point X="477" Y="227" T="1" />
 	<Point X="477" Y="227" T="1" />
 	</Gesture>