<?xml version='1.0' encoding='utf8'?>
<Gesture Name="Three10" Subject="1" Speed="Medium" Number="10" NumPts="125" Milliseconds="1024" AppName="Gestures" AppVersion="1.0.0.0" Date="Monday, April 17, 2023" TimeOfDay="00:36:14 AM"><Point X="188" Y="73" T="1" />
 	<Point X="189" Y="73" T="1" />
 	<Point X="191" Y="73" T="1" />
 	<Point X="193" Y="73" T="1" />
 	<Point X="196" Y="73" T="1" />
 	<Point X="203" Y="72" T="1" />
 	<Point X="205" Y="72" T="1" />
 	<Point X="211" Y="72" T="1" />
 	<Point X="213" Y="72" T="1" />
 	<Point X="216" Y="72" T="1" />
 	<Point X="219" Y="72" T="1" />
 	<Point X="222" Y="72" T="1" />
 	<Point X="227" Y="74" T="1" />
 	<Point X="230" Y="75" T="1" />
 	<Point X="235" Y="77" T="1" />
 	<Point X="239" Y="78" T="1" />
 	<Point X="248" Y="82" T="1" />
 	<Point X="252" Y="84" T="1" />
 	<Point X="256" Y="87" T="1" />
 	<Point X="259" Y="88" T="1" />
 	<Point X="264" Y="92" T="1" />
 	<Point X="265" Y="93" T="1" />
 	<Point X="267" Y="97" T="1" />
 	<Point X="269" Y="100" T="1" />
 	<Point X="272" Y="107" T="1" />
 	<Point X="274" Y="112" T="1" />
 	<Point X="276" Y="118" T="1" />
 	<Point X="278" Y="123" T="1" />
 	<Point X="279" Y="127" T="1" />
 	<Point X="281" Y="135" T="1" />
 	<Point X="281" Y="138" T="1" />
 	<Point X="282" Y="142" T="1" />
 	<Point X="282" Y="148" T="1" />
 	<Point X="282" Y="150" T="1" />
 	<Point X="280" Y="157" T="1" />
 	<Point X="279" Y="160" T="1" />
 	<Point X="276" Y="164" T="1" />
 	<Point X="274" Y="168" T="1" />
 	<Point X="272" Y="172" T="1" />
 	<Point X="269" Y="175" T="1" />
 	<Point X="267" Y="178" T="1" />
 	<Point X="265" Y="179" T="1" />
 	<Point X="261" Y="181" T="1" />
 	<Point X="258" Y="183" T="1" />
 	<Point X="257" Y="183" T="1" />
 	<Point X="254" Y="184" T="1" />
 	<Point X="252" Y="185" T="1" />
 	<Point X="250" Y="185" T="1" />
 	<Point X="248" Y="185" T="1" />
 	<Point X="245" Y="185" T="1" />
 	<Point X="243" Y="186" T="1" />
 	<Point X="241" Y="186" T="1" />
 	<Point X="239" Y="186" T="1" />
 	<Point X="237" Y="186" T="1" />
 	<Point X="236" Y="186" T="1" />
 	<Point X="237" Y="186" T="1" />
 	<Point X="237" Y="187" T="1" />
 	<Point X="238" Y="187" T="1" />
 	<Point X="242" Y="187" T="1" />
 	<Point X="244" Y="188" T="1" />
 	<Point X="248" Y="189" T="1" />
 	<Point X="253" Y="191" T="1" />
 	<Point X="257" Y="192" T="1" />
 	<Point X="265" Y="194" T="1" />
 	<Point X="270" Y="196" T="1" />
 	<Point X="274" Y="198" T="1" />
 	<Point X="279" Y="201" T="1" />
 	<Point X="285" Y="204" T="1" />
 	<Point X="288" Y="206" T="1" />
 	<Point X="290" Y="207" T="1" />
 	<Point X="292" Y="210" T="1" />
 	<Point X="293" Y="210" T="1" />
 	<Point X="293" Y="211" T="1" />
 	<Point X="295" Y="214" T="1" />
 	<Point X="296" Y="218" T="1" />
 	<Point X="298" Y="221" T="1" />
 	<Point X="298" Y="224" T="1" />
 	<Point X="299" Y="228" T="1" />
 	<Point X="300" Y="232" T="1" />
 	<Point X="300" Y="234" T="1" />
 	<Point X="300" Y="237" T="1" />
 	<Point X="300" Y="241" T="1" />
 	<Point X="300" Y="245" T="1" />
 	<Point X="300" Y="248" T="1" />
 	<Point X="299" Y="252" T="1" />
 	<Point X="299" Y="254" T="1" />
 	<Point X="298" Y="256" T="1" />
 	<Point X="298" Y="260" T="1" />
 	<Point X="297" Y="261" T="1" />
 	<Point X="295" Y="264" T="1" />
 	<Point X="293" Y="266" T="1" />
 	<Point X="292" Y="267" T="1" />
 	<Point X="292" Y="268" T="1" />
 	<Point X="289" Y="270" T="1" />
 	<Point X="288" Y="270" T="1" />
 	<Point X="286" Y="271" T="1" />
 	<Point X="284" Y="273" T="1" />
 	<Point X="283" Y="274" T="1" />
 	<Point X="282" Y="274" T="1" />
 	<Point X="279" Y="274" T="1" />
 	<Point X="278" Y="275" T="1" />
 	<Point X="273" Y="275" T="1" />
 	<Point X="269" Y="275" T="1" />
 	<Point X="259" Y="275" T="1" />
 	<Point X="250" Y="275" T="1" />
 	<Point X="243" Y="275" T="1" />
 	<Point X="234" Y="275" T="1" />
 	<Point X="230" Y="275" T="1" />
 	<Point X="221" Y="277" T="1" />
 	<Point X="215" Y="277" T="1" />
 	<Point X="211" Y="277" T="1" />
 	<Point X="209" Y="277" T="1" />
 	<Point X="205" Y="277" T="1" />
 	<Point X="201" Y="276" T="1" />
 	<Point X="197" Y="276" T="1" />
 	<Point X="193" Y="275" T="1" />
 	<Point X="189" Y="275" T="1" />
 	<Point X="185" Y="275" T="1" />
 	<Point X="179" Y="274" T="1" />
 	<Point X="177" Y="273" T="1" />
 	<Point X="176" Y="273" T="1" />
 	<Point X="174" Y="273" T="1" />
 	<Point X="173" Y="273" T="1" />
 	<Point X="173" Y="272" T="1" />
 	<Point X="173" Y="272" T="1" />
 	</Gesture>